{
  "timestamp": "2026-04-03T20:09:07.446298",
  "model": "mistral:latest",
  "keyword_count": 3,
  "analyze_subtitles": true,
  "analysis_source": "youtube",
  "keywords": [
    {
      "keyword": "오늘의 주요 뉴스",
      "is_fixed": true,
      "views": [
        457
      ],
      "video_count": 1,
      "videos": [
        {
          "title": "[News Briefing] Today's Top News / SBS",
          "video_id": "KeLXoc9K1wQ",
          "views": 457,
          "upload_date": "2026-04-03",
          "url": "https://www.youtube.com/watch?v=KeLXoc9K1wQ",
          "subtitle_summary": "1. 4월 3일 금요일입니다. 주영진의 뉴스브리핑이 시작되었으며, 첫 소식으로 Trump 미국 대통령이 이란에 대한 고강도 공격을 예고했다는 소식이 있었습니다. Trump은 SNS를 통해 교량과 발전소를 지목하였고, 신속하게 이뤄져야 할 새로운 정권 지도부에 대한 것을 알고 있음을 밝혔습니다.\n2. 마크롱 프랑스 대통령은 현재 한국을 방문하고 있으며, 이재명 대통령과 한불 정상회담을 했습니다. 두 정상은 조금 전 공동 언론 발표를 통해서 두 나라 사이의 경제 협력과 교역, 투자 규모를 확대하는 등 두 나라 관계를 글로벌 전략적 동반자 관계로 격상하기로 합의했습니다.\n3. 대구시장 후보인 김부겸 전 국무총리가 민주당에서 제명되었고, 피해자인 50대 여성과 딸은 사위에게 가정폭력을 당하며 좁은 신혼 원룸에서 함께 생활했다는 조사결과가 있었습니다.",
          "db_saved": true
        }
      ],
      "max": 0,
      "min": 0,
      "nb_score": 0,
      "avg_views": 0,
      "total_views": 0
    },
    {
      "keyword": "서울시장 경선",
      "is_fixed": false,
      "views": [
        2652,
        1374
      ],
      "video_count": 2,
      "videos": [
        {
          "title": "[LIVE] 더불어민주당 서울시장 후보자 2차 경선 합동토론회/2026년 4월 3일(금)/KBS",
          "video_id": "AJas3DgdpNg",
          "views": 2652,
          "upload_date": "2026-04-03",
          "url": "https://www.youtube.com/watch?v=AJas3DgdpNg",
          "subtitle_summary": "1. 더불어민주당, 중앙당, 선관위가 주최한 서울시장 후보자 합동토론회는 KBS에서 진행되고 있습니다. 이번 토론은 930만 서울 시민의 삶과 꿈을 위해 책임지는 시장의 어깨에 무거운 문제들을 함께 해결하고자 합니다.\n2. 오늘 토론에 참석한 세 명의 후보로는 전현희, 정원호, 박주민이 있으며, 공통 질문과 부동산과 민생 경제를 주제로 하는 주도권 토론이 진행됩니다.\n3. 이번 합동 토론은 KBS 홈페이지와 KBS 유튜브 뉴스 채널, 그리고 더불어민주당 유튜브 델리주를 통해서 실시간으로 함께하실 수 있습니다.",
          "db_saved": true
        },
        {
          "title": "[LIVE] 더불어민주당 서울특별시장 본경선 합동토론회 | KBS",
          "video_id": "tnZl4a4jN0g",
          "views": 1374,
          "upload_date": "2026-04-03",
          "url": "https://www.youtube.com/watch?v=tnZl4a4jN0g",
          "subtitle_summary": "1. 토론회는 더불어민주당, 중앙당, 선관위가 주최하고 KBS가 주관한 서울특별시장 후보자 합동 토론회입니다.\n2. 토론의 주제는 공통 질문과 부동산, 민생경제를 포함하며 후보들이 왜 더불어민주당 서울시장 후보가 되어야 하는지 발언합니다.\n3. 토론은 공통 질문과 자유로운 주제의 주도권 토론, 코너, 후보들의 마무리 발언으로 이루어집니다. 실시간으로 함께하는 방법은 KBS 홈페이지, KBS 유튜브 뉴스 채널과 더불어민주당 유튜브 델리주입니다.",
          "db_saved": true
        }
      ],
      "max": 3.4961,
      "min": 0.0,
      "nb_score": 34961.086,
      "avg_views": 2013.0,
      "total_views": 4026
    },
    {
      "keyword": "국회 정상회담 호르무즈 협력",
      "is_fixed": false,
      "views": [
        9570,
        10145,
        2196,
        5
      ],
      "video_count": 4,
      "videos": [
        {
          "title": "[LIVE] [속보] 이 대통령 \"한·프, 호르무즈 안전 수송로 확보 협력하기로\"...한-프랑스 공동언론발표 [이슈현장] / JTBC News",
          "video_id": "rnmJ9Gtmr7Y",
          "views": 9570,
          "upload_date": "2026-04-03",
          "url": "https://www.youtube.com/watch?v=rnmJ9Gtmr7Y",
          "subtitle_summary": "대한민국 대통령 이재명과 프랑스 공화국 대통령 에마넬 마크롱은 정상회담을 통해 양국 관계를 글로벌 전략적 동반자 관계로 격상하고, 협력을 강화하기로 했습니다. 이에 대한민국과 프랑스는 교육 및 투자를 더욱 확대할 계획이며, 신산업 분야에서의 상호투자와 투자 기업의 고용 증진을 목표로 하고 있습니다. 또한 첨단과학과 미래산업 분야에서의 공동성장, 인공지능 반도체 양자분야 협력, 원자력 시장 공동진출, 해상 폭력 발전 산업의 성장, 핵심 광물 공급망 협력, 우주, 방산 등 미래 안보 분야에서의 상호 보완적인 협력을 강화하고자 합니다. 또한 양국 문화 협력을 강화하여 인적 교류 100만 명 시대를 열어가기로 했습니다.",
          "db_saved": true
        },
        {
          "title": "President Lee: \"France Agrees to Cooperate on Securing Safe Transport Routes in the Strait of Hor...",
          "video_id": "pnShN3qaqLs",
          "views": 10145,
          "upload_date": "2026-04-03",
          "url": "https://www.youtube.com/watch?v=pnShN3qaqLs",
          "subtitle_summary": "대한민국 대통령 이재명과 프랑스 공화국 대통령 마크롱은 정상회담에서 양국 관계를 글로벌 전략적 동반자 관계로 격상하고, 3개의 협정을 개정하고 11개의 양해 각설을 체결했습니다. 이번 회담의 구차적인 성과는 다음과 같습니다:\n1. 양국간 경제 협력을 강화하여 교육 및 투자를 더욱 확대하고, 2030년 200억불 달성을 목표로 합니다.\n2. 첨단 과학과 미래산업 분야에서의 공동 성장을 도모하고, 인공지능 반도체 양자분야 협력 의향서와 같은 중요한 발판을 마련합니다.\n3. 양국 우호관계의 핵심인 문화 협력을 강화하고, 인적 교류 100만 명 시대를 열어가기 위해서 노력합니다.",
          "db_saved": true
        },
        {
          "title": "[현장영상+] \"호르무즈 해협 내 안전한 해상수송로 확보 협력\" / YTN",
          "video_id": "IjXFcNpmJoA",
          "views": 2196,
          "upload_date": "2026-04-03",
          "url": "https://www.youtube.com/watch?v=IjXFcNpmJoA",
          "subtitle_summary": "1. 대한민국 대통령 이재명과 프랑스 대통령 마크롱은 양국의 관계를 글로벌적인 전략적 동반자 관계로 개선하고, 교육, 투자, 신산업 분야에서의 상호 투자 및 혁신을 강화하기로 했습니다.\n2. 양국은 인공지능, 반도체, 원자력 등 첨단과학과 미래산업 분야에서의 공동성장을 추구하고, 핵심 광물 공급망 협력 및 우주, 방산 분야에서도 상호 보완적인 협력을 확대할 계획입니다.\n3. 양국은 문화 협력을 강화하고, 인적 교류를 활발히 유지하기 위해 한불 문화 기술 협정 개정, 항공 협정 등을 통해 양국의 미래 세대가 서로를 더 잘 이해할 수 있도록 노력할 계획입니다.",
          "db_saved": true
        },
        {
          "title": "\"호르무즈 해협 수송로 확보 협력!\" 엄청난 성과들 줄줄 이끌어낸 한-프 정상회담",
          "video_id": "buSwZAmgi_g",
          "views": 5,
          "upload_date": "2026-04-03",
          "url": "https://www.youtube.com/watch?v=buSwZAmgi_g",
          "subtitle_summary": "대한민국 대통령 이재명과 프랑스 공화국 대통령 마크롱이 진행한 정상회담에서, 양국의 관계를 글로벌 전략적 동반자 관계로 격상하고, 3개의 협정을 개정하고 11개의 양해 각서를 체결했습니다. 이번 회담에서는 교육 및 투자를 더욱 확대하여 2030년까지 200억불을 목표로 하고, 첨단 과학과 미래산업 분야에서의 공동성장을 도모하며, 양국 우호관계의 핵심인 문화 협력을 강화하여 인적 교류 100만 명 시대를 열어가기로 했습니다.",
          "db_saved": true
        }
      ],
      "max": 2.1189,
      "min": 1.8614,
      "nb_score": 1.1383,
      "avg_views": 5479.0,
      "total_views": 21916
    },
    {
      "keyword": "검찰 총장 직무대행",
      "is_fixed": false,
      "views": [
        299161,
        23451,
        68898
      ],
      "video_count": 3,
      "videos": [
        {
          "title": "[현장영상] \"판사가 선고 못할 사이즈\" 충격 녹취…검찰총장 대행 '멘붕 ' / JTBC News",
          "video_id": "n2HnaQc71Og",
          "views": 299161,
          "upload_date": "2026-04-03",
          "url": "https://www.youtube.com/watch?v=n2HnaQc71Og",
          "subtitle_summary": "1. 검찰총장은 확인했으나, 수사가 사건을 설계하거나 결론을 정해놓고 가지는 것은 아니며, 이러한 경우에는 잘못된 것입니다.\n2. 검사가 피고인에게나 변호인에게 \"협조하라\" 식으로 제안하면 어떻게 되는지 의문이 들었습니다.\n3. 현재 보도와 관련된 내용을 따라하면, 이재명과 같이 공범으로 고소될 것이며, 결국 재판이 가능한 사이즈가 되어 재판장이 성할 수 없는 상황이 될 것입니다.",
          "db_saved": true
        },
        {
          "title": "법무부장관도, 검찰총장 직무대행도 \"이런 수사는 처음 봅니다\" 답정너 수사에 소름!",
          "video_id": "Fq_-S7XpZek",
          "views": 23451,
          "upload_date": "2026-04-03",
          "url": "https://www.youtube.com/watch?v=Fq_-S7XpZek",
          "subtitle_summary": "1. 수사 과정에서 조건과 노출을 가진 동기로 인해 정부 조사가 잘못되었다고 의견이 제기됐으나, 법무부장관은 적법하게 이루어졌음을 강조했습니다.\n2. 쌍방울 주가 조작 사건이 시작되었고, 이화영 부지사의 법인 카드 사건이 발생했습니다. 중요한 주가 조작 사건은 빠져나갔으며, 쌍방울 대북 소금 사건으로 전환되었습니다.\n3. 이재명 경기도에 대한 쌍방울의 대북 선급 대납 사건으로 또 변질되었고, 이 사건은 오늘 확인되는 조작 수사 과정을 통해서 기소가 이루어지고 있음을 설명했습니다.",
          "db_saved": true
        },
        {
          "title": "검찰 대선배의 날카로운 돌직구!!! 난감한...검찰총장 직무대행",
          "video_id": "IOVWZcxg-48",
          "views": 68898,
          "upload_date": "2026-04-03",
          "url": "https://www.youtube.com/watch?v=IOVWZcxg-48",
          "subtitle_summary": "1. 국경원에서 광주 서구 조사를 진행하고 있습니다. 검찰총장 직무대행을 위해 지릴 것입니다.\n2. 검사가 수사를 할 때 적법한 절차에서 증거를 수집하고 분석합니다. 증거가 없으면 불기소하며, 있으면 기소합니다.\n3. 최근 박상용 검사의 녹체록을 통해 이재명 당시 민주당 대표를 기소해야 한다는 결정이 내려졌으며, 그 결정에 맞는 진술을 만들어내고 있습니다. 이를 위해서 변호사와 협박하고 있으며, 원인 스스로 녹치기 보면 흡수한다는 내용까지 나옵니다.",
          "db_saved": true
        }
      ],
      "max": 1.2796,
      "min": 2.3433,
      "nb_score": 0.5461,
      "avg_views": 130503.33,
      "total_views": 391510
    },
    {
      "keyword": "코스피 상승 외국인 매수",
      "is_fixed": false,
      "views": [
        281,
        599,
        429
      ],
      "video_count": 3,
      "videos": [
        {
          "title": "코스피 2.5% 상승 5,300선 '탈환'...환율 1,505원 / YTN",
          "video_id": "jzdHqCivzSY",
          "views": 281,
          "upload_date": "2026-04-03",
          "url": "https://www.youtube.com/watch?v=jzdHqCivzSY",
          "subtitle_summary": "1. 코스피는 오늘 5,300선을 회복하며 장을 마감했습니다. 이는 외국인의 매수로 인한 지속적인 상승세 때문입니다.\n2. 코스피 대장주인 삼성전자, SK 하이닉스, 현대차 등 조선업종과 불확실성에 대한 수요가 강세를 보였습니다.\n3. 원달러 환율은 오늘 하락세였으며, 주간 거래가 시작할 당시보다 1500점 1505.2원에 거래됐습니다. 미국 시장 등이 휴장하는 금요일인 성 금요일에는 불확실성과 변동성이 여전히 남아 있습니다.",
          "db_saved": true
        },
        {
          "title": "마감시황] 4/3 호르무즈 기대에 반등마감 / 외국인 순매수 귀환 / 변동성속 삼전,닉스 상승 / 불확실성에 변동성 지속",
          "video_id": "chvMCFGaYb0",
          "views": 599,
          "upload_date": "2026-04-03",
          "url": "https://www.youtube.com/watch?v=chvMCFGaYb0",
          "subtitle_summary": "1. 4월 3일 금요일 마감시황. 코스피는 5,300포인트 회복했으나 5,400포인트 돌파에 성공하지 못했습니다.\n2. 외국인들이 순수로 매수가 있었고, 숏 커버링도 일부 발생했습니다. 그러나 전반적으로는 불확실성 속에서 변동성이 지속되고 있는 모습입니다.\n3. 트럼프가 또 때리기 위한 협상 마감일인 4월 5일 ~ 6일 까지가 있으므로, 변동성이 크게 확장될 수도 있는 요소가 있습니다.",
          "db_saved": true
        },
        {
          "title": "코스피 2.5% 상승 5,300선 회복...환율 1,504원~1,511원 유지 / YTN",
          "video_id": "qaK6RCasDOc",
          "views": 429,
          "upload_date": "2026-04-03",
          "url": "https://www.youtube.com/watch?v=qaK6RCasDOc",
          "subtitle_summary": "1. 코스피는 오늘 5,300선을 회복하고 5,400 근처에서 상승세를 유지하고 있습니다. 이로 인해 삼성전자 등 대부분의 치가 상승하고 있습니다.\n2. 코스닥은 오늘 1079로 개장하며, 개인이 매수 우의를 나타내고 있습니다.\n3. 원달러 환율은 1,510 근처에서 거래되고 있으나, 전쟁 장기화 예상과 함께 국제유가의 상승은 환율에도 상승 압력을 작용시키고 있습니다. 따라서 환율이 계속 하락할지 아니면 상승세로 전환할지 등의 불확실성은 여전히 남아 있습니다.",
          "db_saved": true
        }
      ],
      "max": 1.5491,
      "min": 4.5005,
      "nb_score": 0.3442,
      "avg_views": 436.33,
      "total_views": 1309
    },
    {
      "keyword": "호르무즈 해협 해상수송로",
      "is_fixed": false,
      "views": [
        2170,
        1584,
        10091,
        2356,
        46132,
        32,
        35
      ],
      "video_count": 7,
      "videos": [
        {
          "title": "[현장영상+] \"호르무즈 해협 내 안전한 해상수송로 확보 협력\" / YTN",
          "video_id": "IjXFcNpmJoA",
          "views": 2170,
          "upload_date": "2026-04-03",
          "url": "https://www.youtube.com/watch?v=IjXFcNpmJoA",
          "subtitle_summary": "1. 이재명 대통령은 프랑스 대통령 마크롱과 함께 양국 관계를 글로벌 전략적 동반자 관계로 격상하고, 공동성명을 체결했습니다.\n2. 두 나라는 경제 협력을 강화하여 교육 및 투자를 확대하고, 신산업 분야에서의 상호 투자와 고용 증진을 목표로 했습니다.\n3. 양국은 첨단과학과 미래산업 분야에서의 공동성장, 인공지능 반도체 협력, 원자력 시장 공동진출, 해상 폭력 발전 산업 성장, 핵심 광물 공급망 협력, 우주, 방산 등 미래 안보 분야에서의 상호 보완적인 협력을 강화하고자 했습니다. 또한 문화 협력을 통해 양국기, 이스포츠 등 새로운 분야의 협력을 확장하고, 인적 교류를 100만 명 시대로 열어가기로 했습니다.",
          "db_saved": true
        },
        {
          "title": "한·프 전략적 동반자 관계 격상...호르무즈 해협 해상수송로 확보 협력",
          "video_id": "94iMFCsBGpY",
          "views": 1584,
          "upload_date": "2026-04-03",
          "url": "https://www.youtube.com/watch?v=94iMFCsBGpY",
          "subtitle_summary": "1. 대한민국 대통령 이재명과 프랑스 공화국 대통령 마크롱은 정상회담에서 양국 관계를 전략적 동반자 관계로 격상하고, 미래 지향적 방향으로 발전시키겠다는 공동성명을 채택했습니다.\n2. 두 국은 교육 및 투자를 강화하여 양국 교육액을 150억 불로 역대 최대치에서 2030년까지 200억불로 목표로 하고, 신산업 분야에서의 상호 투자를 이어나가기 위해 노력할 것입니다.\n3. 양국은 첨단과학과 미래산업 분야에서의 공동성장을 도모하고, 인공지능, 반도체 등 미래 산업 분야의 신성장 동력을 마련할 것으로 예상됩니다. 또한 핵심 광물 공급망 협력 및 우주, 방산 등 미래 안보 분야에서도 상호 보완적인 협력을 확대할 것입니다.",
          "db_saved": true
        },
        {
          "title": "President Lee: \"France Agrees to Cooperate on Securing Safe Transport Routes in the Strait of Hor...",
          "video_id": "pnShN3qaqLs",
          "views": 10091,
          "upload_date": "2026-04-03",
          "url": "https://www.youtube.com/watch?v=pnShN3qaqLs",
          "subtitle_summary": "대한민국 대통령 이재명과 프랑스 공화국 대통령 마크롱은 정상회담에서 양국 관계를 글로벌 전략적 동반자 관계로 격상하고, 3개의 협정을 개정하며 11개의 양해 각설을 체결했습니다. 이번 회담에서는 경제 협력, 첨단 과학과 미래산업 분야, 문화 협력 등 3가지 영역에서 협력하기로 했습니다. 특히 양국이 2030년까지 교육액을 200억불로 확대하고, 신산업 분야에서의 상호 투자를 강화하며, 인공지능, 반도체 등 미래 산업 분야의 성장을 위한 발판을 마련할 계획이 있습니다. 또한 양국 관광객 비즈니스맨 청년 학생들의 교류를 더욱 자유로운 것으로 목표하고 있습니다.",
          "db_saved": true
        },
        {
          "title": "한-프 정상 “호르무즈 해협 수송로 확보 협력”…AI, 원전 등 협력 MOU / KBS  2026.04.03.",
          "video_id": "SrNEfjrFiq0",
          "views": 2356,
          "upload_date": "2026-04-03",
          "url": "https://www.youtube.com/watch?v=SrNEfjrFiq0",
          "subtitle_summary": "1. 이재명 대통령은 마크롱 프랑스 대통령과 정상회담을 갖고, 중동 사태 에너지 위기 등에 공동 대응 방안을 논의했습니다.\n2. 양국 교역액을 2030년까지 200억 달러로 늘리고, 핵심 광물과 원전 등의 협력에도 합의했습니다.\n3. 양국은 '글로벌 전략적 동반자 관계'로 20여 년 만에 격상하기로 했고, 150억 달러 수준인 교역액을 2030년 200억 달러까지 늘리기로 했습니다.",
          "db_saved": true
        },
        {
          "title": "Effectively a 'Maritime Tollgate'... \"Iran's Hormuz Toll to $1 Per Barrel\" | This News Now",
          "video_id": "IQ2wnsvsTBk",
          "views": 46132,
          "upload_date": "2026-04-02",
          "url": "https://www.youtube.com/watch?v=IQ2wnsvsTBk",
          "subtitle_summary": "1. 중동전쟁의 결과로, 이ран은 호르무즈 해상을 봉쇄하고 전세계 해상 원유 수송량의 20%가 통과하는 전략적 요충지입니다.\n2. 최근, 이ран 의회는 이곳을 지나는 유조선에 통행료를 부과하는 신규 관리 계획을 승인했습니다. 각 선박에 배럴당 약 1달러의 통행료가 받기로 하였고, 이란 혁명 수비 대측은 화물 명세서와 목적지, 승무원 명단, 위치 정보까지 제출해야 합니다.\n3. 이란의 이번 조치가 현실화될 경우, 중동 전쟁발 국제 유가 상승이 일시적 충격을 넘어 만성적 문제로 자리잡을 수 있다는 우려가 나옵니다.",
          "db_saved": true
        },
        {
          "title": "한·프랑스 정상 “호르무즈 해협 안전 수송로 확보 협력” [KFN 국방뉴스]",
          "video_id": "JAbdvZstB9c",
          "views": 32,
          "upload_date": "2026-04-03",
          "url": "https://www.youtube.com/watch?v=JAbdvZstB9c",
          "subtitle_summary": "1. 한국 대통령 이재명과 프랑스 대통령 에마누엘 마크롱은 정상회담을 통해 글로벌 전략적 동반자 관계로 격상했습니다.\n2. 양국 정상은 중동 전쟁으로 인한 에너지 위기를 극복하기 위해 호르무즈 해협 내 안전한 해상 수송로 확보에 힘을 모으기로 했습니다.\n3. 양국은 원자력 분야의 협력을 강화하고, 호르무즈 해협 내 안전한 해상 수송로 확보를 위해 협력하기로 했으며, 프랑스가 140년 동안 대한민국의 곁을 지켜준 친구라고 인정했습니다.",
          "db_saved": true
        },
        {
          "title": "한-프 '전략적 동반자 관계' 격상...호르무즈 해협 해상수송로 확보에 협력키로",
          "video_id": "gtEAo7IDQ1A",
          "views": 35,
          "upload_date": "2026-04-03",
          "url": "https://www.youtube.com/watch?v=gtEAo7IDQ1A",
          "subtitle_summary": "대한민국 대통령 이재명과 프랑스 공화국 대통령 마크롱은 정상회담에서 양국 관계를 전략적 동반자 관계로 격상하고, 미래 지향적 방향으로 발전시키겠다는 의지가 담긴 공동성명을 채택했습니다. 이어서 교육 및 투자를 확대하여 2030년 200억불 달성을 목표로 한다는 결정을 내렸으며, 신산업 분야에서의 상호 투자와 고용 증진을 추구하기로 했습니다. 또한 첨단과학과 미래산업 분야에서의 공동성장, 인공지능 반도체 양자분야 협력 의향서 및 대한민국 한수원과 프랑스 기업 오라노 플라마톰 간 양해서를 통해 원자력 시장 공동진출, 해상 폭력 발전 산업의 성장, 핵심 광물 산업의 안전 안정적 발전을 위한 토대를 마련하고, 문화 협력을 강화하여 인적 교류 100만 명 시대를 열어가기로 했습니다.",
          "db_saved": true
        }
      ],
      "max": 0.2379,
      "min": 1.0056,
      "nb_score": 0.2365,
      "avg_views": 8914.29,
      "total_views": 62400
    },
    {
      "keyword": "임대차 시장 매물 절벽",
      "is_fixed": false,
      "views": [],
      "video_count": 0,
      "videos": [],
      "max": 0,
      "min": 0,
      "nb_score": 0,
      "avg_views": 0,
      "total_views": 0
    },
    {
      "keyword": "개헌안 공동 발의",
      "is_fixed": false,
      "views": [
        12816
      ],
      "video_count": 1,
      "videos": [
        {
          "title": "[Live] (1) 6개 정당 개헌안 공동발의 합의 (2) 30%가 90%의 세금을 내는 사회 (3) NATO를 탈퇴하는 미국   2026. 04. 02 (목) 오전 08:00",
          "video_id": "wRixGOh19Sw",
          "views": 12816,
          "upload_date": "2026-04-02",
          "url": "https://www.youtube.com/watch?v=wRixGOh19Sw",
          "subtitle_summary": "1. 여섯 개 정당이 3월 31일에 공동 발의한 개헌안을 합의했습니다.\n2. 우리나라는 사회적으로 일부분만이 세금을 내고, 대다수는 별로 세금을 내지 않습니다. 이에 관심이 필요한 변화가 필요합니다.\n3. 미국은 NATO를 탈퇴하려는 것으로 예상됩니다. 이 사안에 대해서 설명을 드리겠습니다.",
          "db_saved": true
        }
      ],
      "max": 0,
      "min": 0,
      "nb_score": 0,
      "avg_views": 0,
      "total_views": 0
    },
    {
      "keyword": "프랑스 화물선 호르무즈 통과",
      "is_fixed": false,
      "views": [],
      "video_count": 0,
      "videos": [],
      "max": 0,
      "min": 0,
      "nb_score": 0,
      "avg_views": 0,
      "total_views": 0
    },
    {
      "keyword": "변호사 감축 촉구 집회",
      "is_fixed": false,
      "views": [],
      "video_count": 0,
      "videos": [],
      "max": 0,
      "min": 0,
      "nb_score": 0,
      "avg_views": 0,
      "total_views": 0
    },
    {
      "keyword": "K배티리 3사 R&D 투자",
      "is_fixed": false,
      "views": [],
      "video_count": 0,
      "videos": [],
      "max": 0,
      "min": 0,
      "nb_score": 0,
      "avg_views": 0,
      "total_views": 0
    },
    {
      "keyword": "의료봉사 다리잃은 사고",
      "is_fixed": false,
      "views": [],
      "video_count": 0,
      "videos": [],
      "max": 0,
      "min": 0,
      "nb_score": 0,
      "avg_views": 0,
      "total_views": 0
    },
    {
      "keyword": "가짜뉴스 사회 문제",
      "is_fixed": false,
      "views": [],
      "video_count": 0,
      "videos": [],
      "max": 0,
      "min": 0,
      "nb_score": 0,
      "avg_views": 0,
      "total_views": 0
    },
    {
      "keyword": "교회 여고생 학대 사건",
      "is_fixed": false,
      "views": [],
      "video_count": 0,
      "videos": [],
      "max": 0,
      "min": 0,
      "nb_score": 0,
      "avg_views": 0,
      "total_views": 0
    },
    {
      "keyword": "실속형 아파트 전월세 시장",
      "is_fixed": false,
      "views": [],
      "video_count": 0,
      "videos": [],
      "max": 0,
      "min": 0,
      "nb_score": 0,
      "avg_views": 0,
      "total_views": 0
    },
    {
      "keyword": "공매도 금지 개미 투자자",
      "is_fixed": false,
      "views": [],
      "video_count": 0,
      "videos": [],
      "max": 0,
      "min": 0,
      "nb_score": 0,
      "avg_views": 0,
      "total_views": 0
    }
  ]
}