{
  "timestamp": "2026-04-10T20:50:54.409993",
  "model": "news-singleline:latest",
  "keyword_count": 3,
  "analyze_subtitles": true,
  "analysis_source": "youtube",
  "keywords": [
    {
      "keyword": "오늘의 주요 뉴스",
      "is_fixed": true,
      "views": [
        598,
        688,
        1061
      ],
      "video_count": 3,
      "videos": [
        {
          "title": "[12 News] Today's Top News / SBS",
          "video_id": "N1gzk-zuYaU",
          "views": 598,
          "upload_date": "2026-04-10",
          "url": "https://www.youtube.com/watch?v=N1gzk-zuYaU",
          "subtitle_summary": "이스라엘의 레바논 공습으로 휴전 협상이 불안정한 상황이 전반적으로 드러났고, 트럼프 대통령은 이스라엘의 공격 자제 가능성을 시사하며 협상에 낙관적인 기대를 나타냈습니다. 네탄야हू 총리는 헤즈볼라 무장 해제 등과 관련하여 레바논 정부와 직접 협상에 나설 계획을 밝혔으며, 이란은 호르무주 해협 통과를 위한 협상을 제안했습니다. 한국은행은 기준 금리를 동결하고 경제 상황을 주시하며, 통일교 금품 수수 의혹 관련 수사결과 전재수, 김교환 의원에 대해 혐의 없음 결정을 내렸습니다.",
          "db_saved": true
        },
        {
          "title": "[News Briefing] Today's Top News / SBS",
          "video_id": "ZH6_IwRdPy8",
          "views": 688,
          "upload_date": "2026-04-10",
          "url": "https://www.youtube.com/watch?v=ZH6_IwRdPy8",
          "subtitle_summary": "이스라엘의 레바논 공습으로 휴전 협상이 불안정한 가운데, 트럼프 전 대통령이 이스라엘의 공격을 옹호하며 상황은 더욱 복잡해지고 있으며, 정병화 외교장관 특사가 이란에 파견되어 선박 안전 및 통항 문제 해결을 위해 협의할 예정입니다.",
          "db_saved": true
        },
        {
          "title": "[Morning Wide] Today's Top News / SBS",
          "video_id": "ZVvb4Auw_5E",
          "views": 1061,
          "upload_date": "2026-04-09",
          "url": "https://www.youtube.com/watch?v=ZVvb4Auw_5E",
          "subtitle_summary": "이란은 미국과의 회담 참석을 결정하고 호르무즈 해협 통과 선박 수를 제한했으며, 이스라엘은 레바논 공격을 자제할 것이라고 발표했습니다. 이재명 대통령은 호르무즈 해협 선박 안전 귀환을 최우선 과제로 지지하고 외교 특사를 파견할 예정입니다. 민주당은 서울과 부산시장 후보를 확정하고, 3차 석유 최고 가격은 동결되었으며, 지방선거를 앞두고 경쟁이 치열해지고 있습니다.",
          "db_saved": true
        }
      ],
      "max": 1.0544,
      "min": 5.0693,
      "nb_score": 0.208,
      "avg_views": 782.33,
      "total_views": 2347
    },
    {
      "keyword": "해군 잠수함 화재",
      "is_fixed": false,
      "views": [
        5952,
        3783,
        5426,
        31
      ],
      "video_count": 4,
      "videos": [
        {
          "title": "현대중 울산조선소서 해군 잠수함 불…실종자 구조중 / 연합뉴스TV (YonhapnewsTV)",
          "video_id": "uP5vMMBBQHY",
          "views": 5952,
          "upload_date": "2026-04-09",
          "url": "https://www.youtube.com/watch?v=uP5vMMBBQHY",
          "subtitle_summary": "[HD 현대중공업 울산조선소에서 해군 잠수함 홍범도함에 불이 났고, 협력업체 소속 여성 AC 1명이 실종되었으나 구조 완료되었으며, 잠수함 재반 정비 작업 중 긴급 대피 조치되었습니다.]",
          "db_saved": true
        },
        {
          "title": "'Ulsan Navy Submarine Fire' Missing Person Found... \"Condition Being Checked\" / SBS",
          "video_id": "B0prqq8QLmo",
          "views": 3783,
          "upload_date": "2026-04-10",
          "url": "https://www.youtube.com/watch?v=B0prqq8QLmo",
          "subtitle_summary": "울산 조선소에서 해군 잠수함 정비 중 발생한 화재로 실종되었던 협력 업체 근로자가 발견되었으며, 현재 상태를 확인하는 데 집중하고 있습니다. 불길은 진화되었으나 정확한 화재 원인은 조사 중이며, 사고 관련자들의 안전을 최우선으로 하고 있습니다. 추가적인 피해는 없는지 면밀히 파악하는 것이 중요합니다.",
          "db_saved": true
        },
        {
          "title": "현대중 울산조선소서 해군 잠수함 불…1명 실종 / 연합뉴스TV (YonhapnewsTV)",
          "video_id": "KWlgziQwJ8g",
          "views": 5426,
          "upload_date": "2026-04-09",
          "url": "https://www.youtube.com/watch?v=KWlgziQwJ8g",
          "subtitle_summary": "[오늘 울산조선소에서 해군 잠수함 화재가 발생, 60대 여성 협력업체 작업자가 실종되었으며, 40여 명이 긴급 대피했다.]",
          "db_saved": true
        },
        {
          "title": "잠수함 화재 구조 이틀째..\"진입 어려워\"",
          "video_id": "71q__gF_0HI",
          "views": 31,
          "upload_date": "2026-04-10",
          "url": "https://www.youtube.com/watch?v=71q__gF_0HI",
          "subtitle_summary": "[현대중공업 잠수함에서 발생한 화재로 고립된 60대 여성 노동자의 구조 작업이 이틀째 난항을 겪고 있으며, 협소한 공간과 내부 전류 문제로 인해 구조가 어려워진 상황이다. 밤새 추가 폭발과 잔불 재발화로 인해 50대 직원도 화상을 입고, 구조 작업은 더욱 지연되고 있다. 현재 여성 노동자는 의식 없는 심정지 상태이며, 화재 원인 규명 및 안전 수칙 준수 여부 조사도 진행 중이다.]",
          "db_saved": true
        }
      ],
      "max": 2.9422,
      "min": 1.7606,
      "nb_score": 1.6711,
      "avg_views": 3798.0,
      "total_views": 15192
    },
    {
      "keyword": "이스라엘 군사 작전",
      "is_fixed": false,
      "views": [
        25614,
        7934,
        29223,
        394
      ],
      "video_count": 4,
      "videos": [
        {
          "title": "[이슈PICK] 이스라엘 '지상전 개시' 레바논 초토화... 최대 규모 군사작전에 베이루트 불바다 / 사건텔러",
          "video_id": "w9RiDzoZnzc",
          "views": 25614,
          "upload_date": "2026-04-09",
          "url": "https://www.youtube.com/watch?v=w9RiDzoZnzc",
          "subtitle_summary": "이스라엘이 헤즈볼라 기반 시설을 겨냥한 최대 규모 공습을 감행하며 레바논 베이루트와 남부 지역을 초토화하고, 혁명 수비대는 공격 중단 시 대응하겠다고 경고했다. 이란은 이스라엘의 휴전합의 무시 행위를 비난하며 미국의 의무를 다할 것이라고 주장했고, 미국은 하르그섬을 타격한 후 이란과의 휴전 합의를 이끌어냈다. 이 휴전은 군사적, 경제적 압박과 타이밍을 결합한 고도 전략적 승부수의 결과로 분석된다.",
          "db_saved": true
        },
        {
          "title": "[🔴속보] 이스라엘, '헤즈볼라 박멸' 마이웨이 선언…\"삐삐 폭발작전 이후 역대 최대 규모 타격 수행\" / 연합뉴스TV(YonhapnewsTV)",
          "video_id": "C-OSl3axYrU",
          "views": 7934,
          "upload_date": "2026-04-09",
          "url": "https://www.youtube.com/watch?v=C-OSl3axYrU",
          "subtitle_summary": "이스라엘이 헤즈볼라 박멸을 선언하며 역대 최대 규모의 타격 작전을 수행하고, 미국과의 휴전 신뢰를 보이지 않고 언제든 공격할 준비가 되어있음을 경고했습니다. 혁명 수비대는 미국에 대한 군사 협력을 중단하고, 주변 골프 국가에도 협력을 중단할 것을 촉구하며, 호르무즈 해협 통행을 중단시키고 있습니다. 이스라엘의 레바논 공습과 함께 긴장이 고조되면서, 파키스탄을 통한 미국과 이란의 종전 협상 시작을 앞두고 있습니다.",
          "db_saved": true
        },
        {
          "title": "[속보] CNN \"헤즈볼라, 휴전 이후 첫 공격…이스라엘에 로켓 발사\"/2026년 4월 9일(목)/KBS",
          "video_id": "t5kgMYQusjk",
          "views": 29223,
          "upload_date": "2026-04-09",
          "url": "https://www.youtube.com/watch?v=t5kgMYQusjk",
          "subtitle_summary": "CNN 보도에 따르면 헤즈볼라가 휴전 이후 첫 공격으로 이스라엘에 로켓을 발사하여 긴장감이 고조되고 있으며, 호르무즈 해협을 통과해야 하는 선박들이 2천척이 넘는 막대한 양으로 대기하고 있어, 안전 확보가 선행되어야 실제 운항 재개가 가능할 것으로 예상된다.",
          "db_saved": true
        },
        {
          "title": "[이슈PICK] 이스라엘, 레바논 본토 전역 폭격... 헤즈볼라 섬멸 작전하자 중동 초토화 / 광화문스퀘어",
          "video_id": "NAO3ai0T9MI",
          "views": 394,
          "upload_date": "2026-04-09",
          "url": "https://www.youtube.com/watch?v=NAO3ai0T9MI",
          "subtitle_summary": "이스라엘이 헤즈볼라를 격파하기 위한 레바논 전역 폭격을 감행하며 중동 지역의 긴장이 고조되고 있으며, 이스라엘의 공격에 레바논 혁명 수비대는 대응을 예고하고, 이란은 이스라엘에 대한 공격 중단을 조건으로 휴전 합의를 이루었으나, 상황은 여전히 불안정하다.",
          "db_saved": true
        }
      ],
      "max": 2.0755,
      "min": 1.9071,
      "nb_score": 1.0883,
      "avg_views": 15791.25,
      "total_views": 63165
    },
    {
      "keyword": "소상공인 단결권",
      "is_fixed": false,
      "views": [
        1354,
        286,
        1425,
        32,
        2057
      ],
      "video_count": 5,
      "videos": [
        {
          "title": "[오늘무슨일] 李대통령 \"정규직이 혜택 독점 안돼... 소상공인 단결권 허용해야\"",
          "video_id": "Wp54U4Xy3j8",
          "views": 1354,
          "upload_date": "2026-04-10",
          "url": "https://www.youtube.com/watch?v=Wp54U4Xy3j8",
          "subtitle_summary": "[이 대통령은 정규직의 혜택 독점 문제를 지적하며, 소상공인의 단결권을 허용해야 한다고 주장했습니다. 노동 정책이 오히려 노동자들에게 불리하게 작용하고, 노동 양극화를 심화시킨다고 비판하며, 상식적인 대화를 통해 국민적 공감대를 형성해야 한다고 강조했습니다. 특히, 정규직과 비정규직 간의 임금 격차 문제에 대한 개선 방안을 모색해야 한다고 밝혔습니다.]",
          "db_saved": true
        },
        {
          "title": "\"소상공인도 집단교섭 허용해야!\" 대통령 '파격'주장에 간담회장 '깜짝'!",
          "video_id": "uxENrMPmog8",
          "views": 286,
          "upload_date": "2026-04-10",
          "url": "https://www.youtube.com/watch?v=uxENrMPmog8",
          "subtitle_summary": "대통령은 소상공인까지 집단교섭을 허용해야 한다는 파격 주장을 펼치며, 중동 전쟁으로 악화된 경제 상황과 노동 존중 사회 구축 노력의 한계를 인정했습니다. 노동계의 불만을 해소하고 산업 경제 발전을 위한 조정 노력을 강조하며, 노동조합법 교정, 노동절 명칭 보건 공유지 제도 등 기존 성과를 언급했습니다. 특히 산업재 사망자 감소, 안전 시설 미비 문제 해결, 임금 격차 및 고용 안정성 문제 해결에 노동계의 참여를 촉구하며, 감시원 충원 등 구체적인 방안을 검토하겠다고 밝혔습니다.",
          "db_saved": true
        },
        {
          "title": "[자막] 이재명 대통령, 민주노총과 90분 대화 \"정규직·비정규직 모순 풀고 산업안전 차별 없애자\"",
          "video_id": "jiWKNYOi5Ds",
          "views": 1425,
          "upload_date": "2026-04-10",
          "url": "https://www.youtube.com/watch?v=jiWKNYOi5Ds",
          "subtitle_summary": "이재명 대통령이 민주노총과 90분 대화에서 노동 시장 양극화 해소, 산업 전환 대응, 비정규직 문제 해결 등 주요 과제에 대한 협력을 약속하며 신뢰를 바탕으로 한 지속적인 소통을 당부했다. 산업 안전 분야의 차별 없는 적용과 5인 미만 사업장 근로 기준법 확대 등 구체적인 정책 제안이 있었고, 위기 산업 대책 마련 및 노조 조직률 제고 등 보편적인 과제에 대한 공감대를 형성했다. 정부는 모범적인 사용자 역할을 수행하고 노동계의 현장 제안을 적극 수용하여 상생 가능한 정책을 추진하겠다는 의지를 밝혔다.",
          "db_saved": true
        },
        {
          "title": "\"정규직만 챙기면 다음 세대는 죽는다\" 이재명이 민주노총에 날린 직격탄",
          "video_id": "HvWEA6AteHc",
          "views": 32,
          "upload_date": "2026-04-10",
          "url": "https://www.youtube.com/watch?v=HvWEA6AteHc",
          "subtitle_summary": "[이재명 이 대표는 민주노총과의 면담에서 미래 세대의 위협을 강조하며, 노동자들의 약자성을 해결하기 위한 조직화와 집단 교섭의 중요성을 역설했다. 공정 거부 등 불합리한 규제를 완화하고, 노동조합 조직률을 높이기 위한 정부 정책을 적극 검토할 것을 촉구하며, 중간 착취 문제 해결과 사회 안전망 강화 방안을 제시했다.]",
          "db_saved": true
        },
        {
          "title": "이 대통령 “2년 기간제법, 노동 보호 아닌 고용금지법 돼버려…대안 필요” / KBS  2026.04.10.",
          "video_id": "j8ZgzSyiwRc",
          "views": 2057,
          "upload_date": "2026-04-10",
          "url": "https://www.youtube.com/watch?v=j8ZgzSyiwRc",
          "subtitle_summary": "이 대통령은 현행 2년 기간제법이 실질적으로 ‘2년 고용 금지법’으로 전락하여 비정규직 노동자를 방치하는 결과를 초래한다고 보고 개선 필요성을 강조했습니다. 정규직 전환을 유도하는 법안이 오히려 고용을 제한하는 방향으로 작용하고 있으며, 노조 조직력 차이와 소상공인의 집단교섭 허용 등 현실적인 대안 마련이 시급하다고 밝혔습니다. 또한, 노사정 사회적 대화 복귀와 AI 일자리 전환에 대한 공동 대응을 촉구하며 노동계 현장의 목소리를 반영할 것을 요청했습니다.",
          "db_saved": true
        }
      ],
      "max": 1.6647,
      "min": 1.7943,
      "nb_score": 0.9278,
      "avg_views": 1030.8,
      "total_views": 5154
    },
    {
      "keyword": "이란 미국 대면 협상",
      "is_fixed": false,
      "views": [
        3342,
        2680,
        970
      ],
      "video_count": 3,
      "videos": [
        {
          "title": "미국·이란 내일 대면...종전 협상 최대 변수는? / YTN",
          "video_id": "YjdlYkGdZNs",
          "views": 3342,
          "upload_date": "2026-04-10",
          "url": "https://www.youtube.com/watch?v=YjdlYkGdZNs",
          "subtitle_summary": "미국과 이란이 내일 대면 협상을 통해 종전을 논의하지만, 첫 협상인 만큼 완전한 타결 가능성은 낮아 보이며, 이견 해소보다는 추후 약속 정도만 이루어질 가능성이 크다. 벤스 부통령의 참석은 신뢰성을 높일 수 있지만, 국제 협상 경험 부족으로 실행 가능성에 대한 의문이 남아있고, 트럼프 대통령이 벤스 부통령을 활용하여 마가 성주파의 승리를 확보하려는 의도가 관찰된다. 무력 충돌 가능성 또한 배제할 수 없는 상황이다.",
          "db_saved": true
        },
        {
          "title": "[🔴속보] 미국·이란 종전 협상 D-1…美 대표단에 '차기 잠룡' 밴스·트럼프 사위 쿠슈너·위트코프 특사 / 연합뉴스TV(YonhapnewsTV)",
          "video_id": "NwIJ8WBHIUA",
          "views": 2680,
          "upload_date": "2026-04-10",
          "url": "https://www.youtube.com/watch?v=NwIJ8WBHIUA",
          "subtitle_summary": "트럼프 전 대통령이 나토에 대한 비판을 이어가고 있으며, 이란과의 종전 협상에 대해 낙관적인 입장을 보이고 있습니다. 이란 지도부는 이스라엘의 레바논 타격이 휴전 합의 위반이라고 비판하며, 이스라엘이 헤즈볼라의 무장 해제를 위해 레바논 정부와 직접 협상하겠다고 발표했습니다. 호르무즈 해협의 관리 수준을 격상하겠다고 이란 최고 지도자가 밝히며, 미국과의 협상 장소로 파키스탄 총리 관저가 거론되고 있습니다.",
          "db_saved": true
        },
        {
          "title": "First U.S.-Iran Face-to-Face Negotiations Tomorrow Amid Israeli 'Deal-Stopping' Airstrike (April ...",
          "video_id": "Y-xws2I1ASg",
          "views": 970,
          "upload_date": "2026-04-10",
          "url": "https://www.youtube.com/watch?v=Y-xws2I1ASg",
          "subtitle_summary": "미국과 이란이 파키스탄에서 첫 종전 협상을 시작하지만, 이스라엘의 지속적인 공습으로 협상 전망은 불투명하며, 호르무즈 해협 통행과 우라늄 농축 권한 등 주요 쟁점에 입장 차이가 큽니다. 동시에 이스라엘은 레바논 베이루트 남부 공습을 지속하며 갈등을 고조시키고 있으며, 450명의 환자가 병원에서 대피하지 못한 채 불안에 직면했습니다.",
          "db_saved": true
        }
      ],
      "max": 2.3269,
      "min": 3.4649,
      "nb_score": 0.6716,
      "avg_views": 2330.67,
      "total_views": 6992
    },
    {
      "keyword": "호르무즈 해협 봉쇄",
      "is_fixed": false,
      "views": [
        19952,
        64890,
        1150,
        6460,
        17080,
        61321,
        37839,
        5944
      ],
      "video_count": 8,
      "videos": [
        {
          "title": "Iran Re-blockades 'Hormuz'... Proposes Alternative Route After Failing to Clear Mines [News Playl...",
          "video_id": "DVDP3NKhYAE",
          "views": 19952,
          "upload_date": "2026-04-09",
          "url": "https://www.youtube.com/watch?v=DVDP3NKhYAE",
          "subtitle_summary": "이란이 호르무주 해협 재봉쇄 가능성을 시사하며, 이스라엘의 우려 속에 미국과 이란 대표단 간의 휴전 협상이 진행 중인 가운데, 이스라엘이 레바논을 지속적으로 공격하며 협상에 차질을 빚고 있다.",
          "db_saved": true
        },
        {
          "title": "[🔴이슈를 켜라] [속보] 이란, 호르무즈 재봉쇄에 유조선 긴급 유턴 / 채널A",
          "video_id": "DxZF0E2ss8s",
          "views": 64890,
          "upload_date": "2026-04-09",
          "url": "https://www.youtube.com/watch?v=DxZF0E2ss8s",
          "subtitle_summary": "이란이 호르무즈 해협을 재차 봉쇄하면서 국제 해상 운송에 차질이 빚어지고 있으며, 이는 세계 유가 급등의 원인이 될 수 있다는 우려가 커지고 있습니다. 미국은 벤 스나이더 부통령을 파견하여 협상을 재개하려 하지만, 이란은 이스라엘의 레바논 공격과 휴전 방해라는 이유를 내세워 불확실성을 더하고 있습니다. 호르무즈 해협의 자유로운 항해권 확보를 위한 국제적인 노력에도 불구하고, 이란의 움직임은 상황을 더욱 복잡하게 만들고 있습니다.",
          "db_saved": true
        },
        {
          "title": "이란이 호르무즈 해협을 봉쇄했다… 미국의 초강수!",
          "video_id": "tlTMKfBuQvs",
          "views": 1150,
          "upload_date": "2026-04-10",
          "url": "https://www.youtube.com/watch?v=tlTMKfBuQvs",
          "subtitle_summary": "호르무즈 해협 통과 선박이 극소수이며, 이란의 지속적인 협상 거부와 휴전 기간 내 해협 폐쇄는 합의의 불안정성을 드러내고 있으며, 이스라엘의 헤즈볼라 공격과 같은 추가적인 긴장 요소가 휴전 유지에 대한 우려를 증폭시키고 있다.",
          "db_saved": true
        },
        {
          "title": "[속보] 호르무즈 발 담그는 트럼프…이란과 '통행료' 합작 추진/오만 \"호르무즈 통행료 부과 안할 것/2026년 4월 9일(목)/KBS",
          "video_id": "2jLJJuE7s3M",
          "views": 6460,
          "upload_date": "2026-04-10",
          "url": "https://www.youtube.com/watch?v=2jLJJuE7s3M",
          "subtitle_summary": "이란이 호르무즈 해협 통과 선박에 통행료를 부과하려 하자, 미국이 합작 사업을 통해 이익을 얻으려는 방안을 모색하고 있으며, 이에 반대하는 오만 정부가 통행료 부과에 반대 입장을 표명했습니다.",
          "db_saved": true
        },
        {
          "title": "하루 만에 “호르무즈 재봉쇄”…유조선 강제 유턴? / 채널A / 김진의 돌직구쇼",
          "video_id": "YVp2qmEZeuU",
          "views": 17080,
          "upload_date": "2026-04-09",
          "url": "https://www.youtube.com/watch?v=YVp2qmEZeuU",
          "subtitle_summary": "이란이 호르무즈 해협을 재차 봉쇄하면서 국제 유가 급등한 가운데, 미국이 벤 스미스 부통령을 파견하여 휴전 협상을 시도하고 있지만, 이란의 통제 의지와 미국의 자유로운 항해권 인정 원칙 사이의 입장 차이로 인해 협상 난항이 예상된다.",
          "db_saved": true
        },
        {
          "title": "[에디터픽] 휴전 첫날 최대 규모 공습한 이스라엘...이란, 호르무즈 다시 봉쇄  / YTN",
          "video_id": "wKFOfV0Kowc",
          "views": 61321,
          "upload_date": "2026-04-09",
          "url": "https://www.youtube.com/watch?v=wKFOfV0Kowc",
          "subtitle_summary": "이스라엘이 휴전 첫날 레바논에 대대적인 공습을 감행하며 휴전 합의를 위협하고, 호르무즈 해협을 다시 봉쇄하여 긴장이 고조되고 있다. 휴전 대상 국가인지 묻는 가운데 이스라엘은 공격 수위를 높여 상황을 더욱 악화시키고 있으며, 수백 명의 사망자가 발생했다. 미국은 당사국 자제를 촉구했지만, 이란은 보복 경고를 쏟아내며 휴전 파괴 가능성을 시사하고 있다.",
          "db_saved": true
        },
        {
          "title": "[속보] 이란, 호르무즈 재봉쇄에 유조선 긴급 유턴 [뉴스플레이리스트] / 채널A",
          "video_id": "LF1-8Y59h7M",
          "views": 37839,
          "upload_date": "2026-04-09",
          "url": "https://www.youtube.com/watch?v=LF1-8Y59h7M",
          "subtitle_summary": "이란의 호르무즈 해협 봉쇄 가능성이 다시 제기되면서 국제 에너지 시장의 불안감이 커지고 있으며, 이스라엘의 레바논 공격으로 휴전 협상이 난항을 겪고 있는 가운데 미국이 긴장 수위를 높이는 상황이 전개되고 있다.",
          "db_saved": true
        },
        {
          "title": "호르무즈 해협 또 봉쇄?...휴전 합의 시작부터 '흔들' / YTN",
          "video_id": "5puqfmYLgK4",
          "views": 5944,
          "upload_date": "2026-04-09",
          "url": "https://www.youtube.com/watch?v=5puqfmYLgK4",
          "subtitle_summary": "이스라엘이 휴전 합의를 무시하고 레바논 해제볼라를 공격하며 공습을 확대했고, 이에 이란은 호르무즈 해협 봉쇄를 재개하며 대체 항로를 제시했습니다. 휴전 합의 위반으로 이스라엘이 반발하는 가운데, 미국과 이란의 휴전은 불안정한 상황으로 이어지고 있습니다. 네타냐후 총리의 공격은 군사적 의뿐만 아니라 정치적 생존과 재판 리스크를 해소하기 위한 전략적 목적을 가지고 있습니다.",
          "db_saved": true
        }
      ],
      "max": 1.0225,
      "min": 1.5829,
      "nb_score": 0.646,
      "avg_views": 26829.5,
      "total_views": 214636
    },
    {
      "keyword": "지지율",
      "is_fixed": false,
      "views": [
        3244,
        40779,
        1146,
        5970,
        2264,
        1752,
        15910
      ],
      "video_count": 7,
      "videos": [
        {
          "title": "국힘 공개회의 '아수라장'…지지율 두달째 10%대 / 연합뉴스TV (YonhapnewsTV)",
          "video_id": "SOUwx_tgmv0",
          "views": 3244,
          "upload_date": "2026-04-09",
          "url": "https://www.youtube.com/watch?v=SOUwx_tgmv0",
          "subtitle_summary": "국민의힘 최고위 회의가 공천 문제로 인해 아수라장이 된 가운데, 지지율이 10%대에 갇혀 선거 승리를 위한 내부 갈등이 심화되고 있습니다. 양향자, 김재원 최고위원 등 예비 후보들이 맹비난을 퍼부으며 당내 정국이 더욱 복잡해지고 있으며, 장동혁 대표에게 책임이 집중되고 있습니다. 최근 여론 조사에서도 지지율 10%대가 유지되는 가운데, 당내 주요 의원들이 장동혁 대표 사퇴를 촉구하는 등 당 운영에 어려움을 겪고 있습니다.",
          "db_saved": true
        },
        {
          "title": "Lee Jung-hyun calls for a \"30% revolution,\" but People Power Party's approval rating remains at 3...",
          "video_id": "ImfmDqbPLew",
          "views": 40779,
          "upload_date": "2026-04-09",
          "url": "https://www.youtube.com/watch?v=ImfmDqbPLew",
          "subtitle_summary": "민주당은 기업 환경 개선과 지역 경제 살리기를 강조하며 호남 지역을 방문했고, 국민의 힘 이정현 전 위원장이 전남 광주 통합시장 출마를 공식 선언하며 경선 경쟁을 예고했습니다. 관세 협상 과정에 대한 긍정적인 평가와 함께 민주당의 텃밭 다지기 노력과 국민의 힘의 여당 견제민심 흡수 전략이 맞물린 가운데, 호남 지역 지지율 격차가 뚜렷하게 나타났습니다.",
          "db_saved": true
        },
        {
          "title": "이 대통령 지지율 67% 최고치 유지...민주 48%·국민의힘 20% / YTN",
          "video_id": "St0bEH52wJ8",
          "views": 1146,
          "upload_date": "2026-04-10",
          "url": "https://www.youtube.com/watch?v=St0bEH52wJ8",
          "subtitle_summary": "이 대통령 지지율이 취임 후 최고치인 67%를 기록하며 2주 연속 유지되었고, 고유가 피해 지원금에 대한 긍정 평가가 52%로 나타났습니다. 더불어민주당이 48%의 지지율을 확보했으며, 국민의힘은 20%로 조사되었습니다. 이번 여론조사는 한국갤럽이 성인 남녀 100명을 대상으로 지난 7일부터 9일까지 실시했습니다.",
          "db_saved": true
        },
        {
          "title": "개헌 찬성 '48.0%→56.5%'…이 대통령 지지율 67.3% [말하는 기자들_정치정책_0409]",
          "video_id": "CnzI1n3Dceg",
          "views": 5970,
          "upload_date": "2026-04-09",
          "url": "https://www.youtube.com/watch?v=CnzI1n3Dceg",
          "subtitle_summary": "국민 절반 이상이 대통령 개헌 제한에 찬성하며 이재명 대통령 지지율 67.3%로 최고치를 기록했다. 민주당 지지율 또한 50%를 넘으면서 정당 지형이 민주당 우위로 굳어졌고, 민주당 차기 당대표 선거에서는 정청례 대표가 우세를 보였다. 이번 조사는 뉴스마토가 실시한 여론 조사 결과로, 대통령 개헌 찬성 및 이재명 대통령 지지율 상승이 주요 내용이다.",
          "db_saved": true
        },
        {
          "title": "이 대통령 국정 지지율 69%…개헌 동시투표 찬성 61% / 연합뉴스TV (YonhapnewsTV)",
          "video_id": "fgRwHzLYaJE",
          "views": 2264,
          "upload_date": "2026-04-09",
          "url": "https://www.youtube.com/watch?v=fgRwHzLYaJE",
          "subtitle_summary": "이 대통령 국정 지지율이 69%로 최고치를 기록했으며, 긍정 평가와 부정 평가가 비슷한 수준을 유지했습니다. 더불어민주당이 47%로 지지율을 상승시킨 반면, 국민의힘은 18%로 전과 동일했습니다. 개헌 국민투표 동시 실시 찬성 의견이 61%로 반대 의견 23%를 크게 앞서, 동시투표에 대한 지지가 높은 것으로 나타났습니다.",
          "db_saved": true
        },
        {
          "title": "[People Power Party & Polls] The President's approval rating is good, and support for the Democra...",
          "video_id": "i0GmEpVNF_w",
          "views": 1752,
          "upload_date": "2026-04-10",
          "url": "https://www.youtube.com/watch?v=i0GmEpVNF_w",
          "subtitle_summary": "대통령 지지율이 67%로 최고치를 기록하며 긍정적인 평가가 69%까지 상승, 특히 경제 민생과 외교 분야에 대한 지지가 높게 나타났으며, 민주당 지지율 또한 48%로 최고치를 기록했습니다.",
          "db_saved": true
        },
        {
          "title": "[여론조사] 이 대통령 지지율 67.3% '최대치' 개헌 찬성 '48.0%→56.5%' (김성수 배종찬 박주용) #뉴스인사이다 (0409_목)",
          "video_id": "J38G5r5jbIU",
          "views": 15910,
          "upload_date": "2026-04-09",
          "url": "https://www.youtube.com/watch?v=J38G5r5jbIU",
          "subtitle_summary": "이재명 대통령의 국정운영 지지율이 개헌 찬성 여론 상승과 맞물려 최대치인 67.3%를 기록하며 취임 이후 최고치를 달성했다. 개헌 찬성 의견은 56.5%로 2주 전 조사 대비 9% 포인트 상승했으며, 민주당 지지율 또한 50%를 상회하며 최고치를 경신했다. 차기 당대표 선출을 위한 민주당 내 지지율 조사에서는 정청례 대표가 김민석 국무총리, 송영길 전 대표를 앞서며 우위를 점했다.",
          "db_saved": true
        }
      ],
      "max": 0.3508,
      "min": 1.2512,
      "nb_score": 0.2804,
      "avg_views": 10152.14,
      "total_views": 71065
    },
    {
      "keyword": "국제 유가 급등",
      "is_fixed": false,
      "views": [],
      "video_count": 0,
      "videos": [],
      "max": 0,
      "min": 0,
      "nb_score": 0,
      "avg_views": 0,
      "total_views": 0
    },
    {
      "keyword": "미중 회담 논의",
      "is_fixed": false,
      "views": [],
      "video_count": 0,
      "videos": [],
      "max": 0,
      "min": 0,
      "nb_score": 0,
      "avg_views": 0,
      "total_views": 0
    },
    {
      "keyword": "독도 영유권 분쟁",
      "is_fixed": false,
      "views": [],
      "video_count": 0,
      "videos": [],
      "max": 0,
      "min": 0,
      "nb_score": 0,
      "avg_views": 0,
      "total_views": 0
    },
    {
      "keyword": "AI 직업 교육 혁신",
      "is_fixed": false,
      "views": [],
      "video_count": 0,
      "videos": [],
      "max": 0,
      "min": 0,
      "nb_score": 0,
      "avg_views": 0,
      "total_views": 0
    },
    {
      "keyword": "글로벌 에너지 공급망 리스크",
      "is_fixed": false,
      "views": [],
      "video_count": 0,
      "videos": [],
      "max": 0,
      "min": 0,
      "nb_score": 0,
      "avg_views": 0,
      "total_views": 0
    },
    {
      "keyword": "인디 게임 무료 배포",
      "is_fixed": false,
      "views": [],
      "video_count": 0,
      "videos": [],
      "max": 0,
      "min": 0,
      "nb_score": 0,
      "avg_views": 0,
      "total_views": 0
    },
    {
      "keyword": "부산 재보궐선거",
      "is_fixed": false,
      "views": [],
      "video_count": 0,
      "videos": [],
      "max": 0,
      "min": 0,
      "nb_score": 0,
      "avg_views": 0,
      "total_views": 0
    },
    {
      "keyword": "쿠팡 대규모 배당",
      "is_fixed": false,
      "views": [],
      "video_count": 0,
      "videos": [],
      "max": 0,
      "min": 0,
      "nb_score": 0,
      "avg_views": 0,
      "total_views": 0
    }
  ]
}