{
  "timestamp": "2026-04-20T02:00:51.561634",
  "model": "news-singleline:latest",
  "keyword_count": 3,
  "analyze_subtitles": true,
  "analysis_source": "youtube",
  "keywords": [
    {
      "keyword": "오늘의 주요 뉴스",
      "is_fixed": true,
      "views": [],
      "video_count": 0,
      "videos": [],
      "max": 0,
      "min": 0,
      "nb_score": 0,
      "avg_views": 0,
      "total_views": 0
    },
    {
      "keyword": "장특공 폐지안",
      "is_fixed": false,
      "views": [
        2441,
        119
      ],
      "video_count": 2,
      "videos": [
        {
          "title": "Breaking News!! Announcement of Bill Proposed for Phased Abolition of Special Long-Term Holding D...",
          "video_id": "RQ4zy1yPrPU",
          "views": 2441,
          "upload_date": "2026-04-19",
          "url": "https://www.youtube.com/watch?v=RQ4zy1yPrPU",
          "subtitle_summary": "범여권이 1세대 1주택자 특별 공제 단계적 폐지 법안을 발표했으며, 대통령은 이를 “양극화 폭탄”이라는 허위 기사로 반박하며 고가 주택에 대한 공제 문제만 언급, 투기성 주택과 실수요자 구분을 정부가 어떻게 할 것인지 의문임을 지적했다.",
          "db_saved": true
        },
        {
          "title": "[시사쇼 정치다] '장특공제 폐지' 예고에 매물 마를까 우려… 공급 정책은 언제쯤?",
          "video_id": "8DOPajJMpZI",
          "views": 119,
          "upload_date": "2026-04-19",
          "url": "https://www.youtube.com/watch?v=8DOPajJMpZI",
          "subtitle_summary": "[이재명 대통령이 장기 보유자 양도 소득세 혜택 제도인 ‘장특공제’ 폐지를 예고하며 야권과 언론의 비판을 반박, 거주 여부와 관계없이 장기 보유 사실만으로 세금을 깎아주는 제도가 세금 폭탄이나 투기 조장 논란을 야기할 수 있다는 우려를 표명했습니다.]",
          "db_saved": true
        }
      ],
      "max": 2.7601,
      "min": 2.4141,
      "nb_score": 1.1434,
      "avg_views": 1280.0,
      "total_views": 2560
    },
    {
      "keyword": "미국 이란 협상 재개",
      "is_fixed": false,
      "views": [],
      "video_count": 0,
      "videos": [],
      "max": 0,
      "min": 0,
      "nb_score": 0,
      "avg_views": 0,
      "total_views": 0
    },
    {
      "keyword": "호르무즈 선박 항행",
      "is_fixed": false,
      "views": [],
      "video_count": 0,
      "videos": [],
      "max": 0,
      "min": 0,
      "nb_score": 0,
      "avg_views": 0,
      "total_views": 0
    },
    {
      "keyword": "중동 정세 외교 포럼",
      "is_fixed": false,
      "views": [],
      "video_count": 0,
      "videos": [],
      "max": 0,
      "min": 0,
      "nb_score": 0,
      "avg_views": 0,
      "total_views": 0
    },
    {
      "keyword": "미 대사관 출금 요청",
      "is_fixed": false,
      "views": [],
      "video_count": 0,
      "videos": [],
      "max": 0,
      "min": 0,
      "nb_score": 0,
      "avg_views": 0,
      "total_views": 0
    },
    {
      "keyword": "트럼프 강경 발언",
      "is_fixed": false,
      "views": [],
      "video_count": 0,
      "videos": [],
      "max": 0,
      "min": 0,
      "nb_score": 0,
      "avg_views": 0,
      "total_views": 0
    },
    {
      "keyword": "코스피 6200선 돌파",
      "is_fixed": false,
      "views": [],
      "video_count": 0,
      "videos": [],
      "max": 0,
      "min": 0,
      "nb_score": 0,
      "avg_views": 0,
      "total_views": 0
    },
    {
      "keyword": "원전 건설 반대",
      "is_fixed": false,
      "views": [],
      "video_count": 0,
      "videos": [],
      "max": 0,
      "min": 0,
      "nb_score": 0,
      "avg_views": 0,
      "total_views": 0
    },
    {
      "keyword": "비정규직 노사 교섭",
      "is_fixed": false,
      "views": [],
      "video_count": 0,
      "videos": [],
      "max": 0,
      "min": 0,
      "nb_score": 0,
      "avg_views": 0,
      "total_views": 0
    },
    {
      "keyword": "지역신문 구독 전국화",
      "is_fixed": false,
      "views": [],
      "video_count": 0,
      "videos": [],
      "max": 0,
      "min": 0,
      "nb_score": 0,
      "avg_views": 0,
      "total_views": 0
    },
    {
      "keyword": "고립 가구 돌봄",
      "is_fixed": false,
      "views": [],
      "video_count": 0,
      "videos": [],
      "max": 0,
      "min": 0,
      "nb_score": 0,
      "avg_views": 0,
      "total_views": 0
    },
    {
      "keyword": "증시 전고점 회복",
      "is_fixed": false,
      "views": [],
      "video_count": 0,
      "videos": [],
      "max": 0,
      "min": 0,
      "nb_score": 0,
      "avg_views": 0,
      "total_views": 0
    },
    {
      "keyword": "오페라 공연",
      "is_fixed": false,
      "views": [],
      "video_count": 0,
      "videos": [],
      "max": 0,
      "min": 0,
      "nb_score": 0,
      "avg_views": 0,
      "total_views": 0
    },
    {
      "keyword": "분당 분양가 급등",
      "is_fixed": false,
      "views": [],
      "video_count": 0,
      "videos": [],
      "max": 0,
      "min": 0,
      "nb_score": 0,
      "avg_views": 0,
      "total_views": 0
    },
    {
      "keyword": "석유 대체 자원",
      "is_fixed": false,
      "views": [],
      "video_count": 0,
      "videos": [],
      "max": 0,
      "min": 0,
      "nb_score": 0,
      "avg_views": 0,
      "total_views": 0
    }
  ]
}